{
	"class" : {
		 },
	"instance" : {
		"addCrawlButton" : "PAU 5/31/2020 20:55",
		"addFilterButton" : "js 5/29/2020 12:54",
		"addListMorph" : "PAU 6/1/2020 11:55",
		"addUrlInputField" : "PAU 5/28/2020 20:32",
		"crawlButton" : "PAU 5/25/2020 19:10",
		"crawlButton:" : "js 5/29/2020 11:44",
		"crawler" : "PAU 5/25/2020 19:12",
		"crawler:" : "PAU 5/25/2020 19:12",
		"filterButton" : "js 5/29/2020 11:42",
		"filterButton:" : "js 5/29/2020 11:45",
		"initialize" : "PAU 6/1/2020 12:18",
		"listMorph" : "PAU 5/31/2020 19:43",
		"listMorph:" : "PAU 5/31/2020 19:43",
		"model" : "PAU 5/31/2020 22:14",
		"model:" : "PAU 5/31/2020 22:14",
		"options" : "PAU 5/25/2020 19:35",
		"options:" : "PAU 5/31/2020 23:33",
		"startCrawling" : "PAU 6/1/2020 12:19",
		"uiLinkFilter" : "js 5/29/2020 11:47",
		"uiLinkFilter:" : "js 5/29/2020 12:55",
		"urlInputField" : "PAU 5/25/2020 18:41",
		"urlInputField:" : "PAU 5/25/2020 18:40" } }
