{
	"class" : {
		 },
	"instance" : {
		"addButtons" : "PAU 8/7/2020 17:51",
		"addListMorph" : "PAU 8/7/2020 17:13",
		"addOutgoingDomainsButton" : "PAU 8/7/2020 17:59",
		"addRegexButton" : "PAU 8/7/2020 18:00",
		"addRegexInputField" : "PAU 8/7/2020 18:19",
		"addRelevantAuthorityButton" : "PAU 8/7/2020 18:00",
		"addSubDomainButton" : "PAU 8/7/2020 18:26",
		"addSubstringButton" : "PAU 8/7/2020 18:03",
		"addSubstringInputField" : "PAU 8/7/2020 18:19",
		"addUIElements" : "PAU 8/7/2020 17:23",
		"crawler" : "js 5/29/2020 12:53",
		"crawler:" : "js 5/29/2020 12:52",
		"defaultBiggerButtonExtent" : "PAU 8/7/2020 17:33",
		"defaultButtonExtent" : "PAU 8/7/2020 17:33",
		"defaultFont" : "PAU 8/5/2020 14:52",
		"defaultInputFieldSize" : "PAU 8/7/2020 17:48",
		"defaultListPosition" : "PAU 8/7/2020 17:12",
		"defaultListSize" : "PAU 8/7/2020 17:13",
		"defaultOutgoingButtonPosition" : "PAU 8/7/2020 17:27",
		"defaultRegexButtonPosition" : "PAU 8/7/2020 17:32",
		"defaultRegexInputFieldPosition" : "PAU 8/7/2020 17:47",
		"defaultRelevantAuthorityPosition" : "PAU 8/7/2020 17:39",
		"defaultSize" : "PAU 8/7/2020 17:16",
		"defaultSubDomainPosition" : "PAU 8/7/2020 17:42",
		"defaultSubstringInputFieldPosition" : "PAU 8/7/2020 17:46",
		"defaultSubstringPosition" : "PAU 8/7/2020 17:44",
		"initialize:" : "PAU 8/7/2020 17:17",
		"links" : "js 5/29/2020 12:58",
		"links:" : "js 5/29/2020 12:57",
		"listMorph" : "js 5/29/2020 13:25",
		"listMorph:" : "js 5/29/2020 13:25",
		"outgoingDomainsButton" : "PAU 8/7/2020 17:57",
		"outgoingDomainsButton:" : "PAU 8/7/2020 17:58",
		"parentDomain" : "PAU 8/7/2020 17:15",
		"parentDomain:" : "PAU 8/7/2020 17:15",
		"regexButton" : "js 5/29/2020 12:10",
		"regexButton:" : "js 5/29/2020 12:10",
		"regexInputField" : "js 5/29/2020 12:07",
		"regexInputField:" : "js 5/29/2020 12:07",
		"relevantAuthorityButton" : "PAU 8/7/2020 17:52",
		"relevantAuthorityButton:" : "PAU 8/7/2020 17:52",
		"searchOutgoing" : "PAU 8/7/2020 18:13",
		"searchRegex" : "PAU 6/18/2020 10:32",
		"searchRelevantAuthority" : "PAU 8/7/2020 17:36",
		"searchSubDomains" : "PAU 8/7/2020 17:41",
		"searchSubstring" : "PAU 7/1/2020 21:35",
		"setOwnAttributes:" : "PAU 8/7/2020 18:14",
		"smallerDefaultFont" : "PAU 8/5/2020 14:53",
		"subDomainButton" : "js 5/29/2020 13:04",
		"subDomainButton:" : "js 5/29/2020 13:04",
		"subStringButton" : "js 6/4/2020 18:12",
		"subStringButton:" : "js 6/4/2020 18:13",
		"subStringInputField" : "js 6/4/2020 18:06",
		"subStringInputField:" : "js 6/4/2020 18:16" } }
